clustree/__init__.py
clustree/_clustree_typing.py
clustree/_config.py
clustree/_config_helpers.py
clustree/_draw.py
clustree/_graph.py
clustree/_handle_pars.py
clustree/_hash.py
clustree/py.typed
clustree-0.2.1.dist-info/LICENSE
clustree-0.2.1.dist-info/WHEEL
clustree-0.2.1.dist-info/METADATA
clustree-0.2.1.dist-info/RECORD
