Metadata-Version: 2.1
Name: clustree
Version: 0.2.1
Summary: Visualize relationship between clusterings at different resolutions
Home-page: https://github.com/ben-j-barlow/clustree
License: GPL-3.0-or-later
Keywords: clustering,visualization,visualisation,clustering-trees,cluster-trees
Author: Ben Barlow
Author-email: ben-j-barlow.1@gmail.com
Requires-Python: >=3.9,<4.0
Classifier: Development Status :: 3 - Alpha
Classifier: License :: OSI Approved :: GNU General Public License v3 or later (GPLv3+)
Classifier: Natural Language :: English
Classifier: Programming Language :: Python :: 3
Classifier: Programming Language :: Python :: 3.9
Classifier: Programming Language :: Python :: 3.10
Classifier: Programming Language :: Python :: 3.11
Classifier: Programming Language :: Python :: 3.9
Classifier: Topic :: Scientific/Engineering :: Artificial Intelligence
Classifier: Topic :: Scientific/Engineering :: Visualization
Classifier: Typing :: Typed
Requires-Dist: igraph (>=0.10.4,<0.11.0)
Requires-Dist: matplotlib (>=3.6,<4.0)
Requires-Dist: networkx (>=3,<4)
Requires-Dist: opencv-python (>=4.7.0.72,<5.0.0.0)
Requires-Dist: pairing-functions (==0.2.1)
Requires-Dist: pandas (>=1.5,<2.0)
Project-URL: Repository, https://github.com/ben-j-barlow/clustree
